{
  "ticker": "ADSK",
  "company": "Autodesk",
  "quarter": "Q3 2025",
  "date": "2025-07-28",
  "content": "Autodesk Financial Overview\nData as of: 2025-07-28\n\nCompany Metrics:\nStock Price: $0.49\nMarket Cap: $1,961,898,459\n52-Week High: $0.63\n52-Week Low: $0.34\n\nValuation Metrics:\nP/E Ratio (TTM): 69.2\nForward P/E: 62.3\nPEG Ratio: 1.18\nPrice to Book: 4.7\n\nFinancial Performance:\nRevenue (TTM): $280,369,327\nRevenue Growth (YoY): 11.2%\nGross Margin: 16.4%\nOperating Margin: 5.3%\nNet Margin: 2.3%\n\nProfitability:\nReturn on Assets: 23.6%\nReturn on Equity: 28.6%\nProfit Margin: 2.3%\n\nTrading Information:\nBeta: 0.56\nDividend Yield: 1.04%\nPrevious Close: $0.48\nDay Range: $0.47 - $0.49\nVolume: 33,159,437\nAverage Volume: 31,129,516",
  "source": "batch-cache",
  "cached_at": "2025-07-28T21:15:02.852154"
}