{
  "ticker": "EXPD",
  "company": "Expeditors International",
  "quarter": "Q3 2025",
  "date": "2025-07-28",
  "content": "Expeditors International Financial Overview\nData as of: 2025-07-28\n\nCompany Metrics:\nStock Price: $2.59\nMarket Cap: $1,558,398,431\n52-Week High: $3.37\n52-Week Low: $1.82\n\nValuation Metrics:\nP/E Ratio (TTM): 13.0\nForward P/E: 11.7\nPEG Ratio: 1.20\nPrice to Book: 7.2\n\nFinancial Performance:\nRevenue (TTM): $346,011,578\nRevenue Growth (YoY): 22.5%\nGross Margin: 65.0%\nOperating Margin: 43.5%\nNet Margin: 9.9%\n\nProfitability:\nReturn on Assets: 2.7%\nReturn on Equity: 20.3%\nProfit Margin: 9.9%\n\nTrading Information:\nBeta: 2.49\nDividend Yield: 0.43%\nPrevious Close: $2.54\nDay Range: $2.52 - $2.65\nVolume: 38,212,323\nAverage Volume: 6,558,929",
  "source": "batch-cache",
  "cached_at": "2025-07-28T21:15:02.803554"
}