{
  "ticker": "MCK",
  "company": "McKesson Corporation",
  "quarter": "Q3 2025",
  "date": "2025-07-28",
  "content": "McKesson Corporation Financial Overview\nData as of: 2025-07-28\n\nCompany Metrics:\nStock Price: $0.24\nMarket Cap: $965,359,569\n52-Week High: $0.31\n52-Week Low: $0.17\n\nValuation Metrics:\nP/E Ratio (TTM): 60.3\nForward P/E: 54.3\nPEG Ratio: 1.73\nPrice to Book: 9.9\n\nFinancial Performance:\nRevenue (TTM): $267,242,318\nRevenue Growth (YoY): 20.2%\nGross Margin: 69.6%\nOperating Margin: 7.7%\nNet Margin: 5.5%\n\nProfitability:\nReturn on Assets: 6.2%\nReturn on Equity: 28.8%\nProfit Margin: 5.5%\n\nTrading Information:\nBeta: 0.58\nDividend Yield: 0.62%\nPrevious Close: $0.23\nDay Range: $0.23 - $0.24\nVolume: 18,130,237\nAverage Volume: 15,513,324",
  "source": "batch-cache",
  "cached_at": "2025-07-28T21:15:02.765740"
}