{
  "ticker": "RTX",
  "company": "RTX Corporation",
  "quarter": "Q3 2025",
  "date": "2025-07-28",
  "content": "RTX Corporation Financial Overview\nData as of: 2025-07-28\n\nCompany Metrics:\nStock Price: $337.91\nMarket Cap: $1,652,629,059,809\n52-Week High: $439.29\n52-Week Low: $236.54\n\nValuation Metrics:\nP/E Ratio (TTM): 18.9\nForward P/E: 17.0\nPEG Ratio: 2.24\nPrice to Book: 5.2\n\nFinancial Performance:\nRevenue (TTM): $401,645,352,772\nRevenue Growth (YoY): 40.3%\nGross Margin: 32.7%\nOperating Margin: 7.7%\nNet Margin: 3.6%\n\nProfitability:\nReturn on Assets: 23.4%\nReturn on Equity: 33.0%\nProfit Margin: 3.6%\n\nTrading Information:\nBeta: 0.82\nDividend Yield: 2.02%\nPrevious Close: $331.15\nDay Range: $327.77 - $344.67\nVolume: 2,761,527\nAverage Volume: 34,216,737",
  "source": "batch-cache",
  "cached_at": "2025-07-28T21:15:02.668773"
}